cool_styles/__init__.py
cool_styles/styles/charcoal.mplstyle
cool_styles/styles/coastalarvest.mplstyle
cool_styles/styles/forestdark.mplstyle
cool_styles/styles/forestlight.mplstyle
cool_styles/styles/goldenpeachy.mplstyle
cool_styles/styles/ivorygrid.mplstyle
cool_styles/styles/sealight.mplstyle
cool_styles-0.3.0.dist-info/METADATA
cool_styles-0.3.0.dist-info/WHEEL
cool_styles-0.3.0.dist-info/licenses/LICENSE
cool_styles-0.3.0.dist-info/RECORD
