Metadata-Version: 2.4
Name: cool_styles
Version: 0.3.0
Summary: A package contaiing a collection of cool matplotlib styles
Author: Giuseppe Minardi
License-File: LICENSE
Requires-Python: >=3.11
Requires-Dist: matplotlib>=3.10.5
